{
	"__comment": "Created by Filal",
	"textures": {
		"particle": "block/resin_bricks3",
		"0": "block/resin_bricks3",
		"1": "block/resin_bricks_top",
		"2": "block/resin_bricks_bottom"
	},
	"elements": [ 	 
		{
			"from": [ 8.000994, 0.000521845, 4.999747 ],
			"to": [ 16.00099, 16.00052, 10.99975 ],
			"faces": {
				"down": { "uv": [ 8, 5, 16, 11 ], "texture": "#2", "cullface": "down" },
				"up": { "uv": [ 8, 5, 16, 11 ], "texture": "#1", "cullface": "up" },
				"north": { "uv": [ 0, 0, 8, 16 ], "texture": "#0" },
				"south": { "uv": [ 8, 0, 16, 16 ], "texture": "#0" },
				"east": { "uv": [ 5, 0, 11, 16 ], "texture": "#0" }
			}
		},
		{
			"from": [ 10.99997, 15.99963, 5.000038 ],
			"to": [ 15.99997, 16.49963, 10.50004 ],
			"faces": {
				"up": { "uv": [ 11, 5, 16, 10.5 ], "texture": "#1" },
				"north": { "uv": [ 16, 5, 11, 5.5 ], "texture": "#1" },
				"south": { "uv": [ 11, 10, 16, 10.5 ], "texture": "#1" },
				"west": { "uv": [ 11, 5, 11.5, 10.5 ], "texture": "#1", "rotation": 270 },
				"east": { "uv": [ 15.5, 5, 16, 10.5 ], "texture": "#1", "rotation": 90 }
			}
		},
		{
			"from": [ 7.999022, 15.99961, 5.499179 ],
			"to": [ 10.49902, 16.49961, 10.49918 ],
			"faces": {
				"up": { "uv": [ 8, 5.5, 10.5, 10.5 ], "texture": "#1" },
				"north": { "uv": [ 10.5, 5.5, 8, 6 ], "texture": "#1" },
				"south": { "uv": [ 8, 10, 10.5, 10.5 ], "texture": "#1" },
				"west": { "uv": [ 8, 5.5, 8.5, 10.5 ], "texture": "#1", "rotation": 270 },
				"east": { "uv": [ 10, 5.5, 10.5, 10.5 ], "texture": "#1", "rotation": 90 }
			}
		},
		{
			"from": [ 11.00087, 0.4999516, 10.9991 ],
			"to": [ 16.00087, 3.999952, 11.4991 ],
			"faces": {
				"down": { "uv": [ 16, 15, 11, 15.5 ], "texture": "#0", "rotation": 180 },
				"up": { "uv": [ 16, 12, 11, 12.5 ], "texture": "#0", "rotation": 180 },
				"south": { "uv": [ 11.01, 12.01, 16, 15.5 ], "texture": "#0" },
				"west": { "uv": [ 11.01, 12.01, 11.49, 15.49 ], "texture": "#0" },
				"east": { "uv": [ 15.5, 12, 15.98, 15.48 ], "texture": "#0" }
			}
		},
		{
			"from": [ 7.999721, 0.4991813, 11.0007 ],
			"to": [ 10.49972, 3.999181, 11.5007 ],
			"faces": {
				"down": { "uv": [ 8.01, 15.01, 10.49, 15.49 ], "texture": "#0" },
				"up": { "uv": [ 10.49, 12.01, 8.01, 12.49 ], "texture": "#0", "rotation": 180 },
				"south": { "uv": [ 8.01, 12.01, 10.49, 15.49 ], "texture": "#0" },
				"west": { "uv": [ 8.01, 12.01, 8.49, 15.49 ], "texture": "#0" },
				"east": { "uv": [ 10.01, 12.01, 10.49, 15.49 ], "texture": "#0" }
			}
		},
		{
			"from": [ 7.999558, 0.5005362, 4.500591 ],
			"to": [ 15.49956, 4.000536, 5.000591 ],
			"faces": {
				"down": { "uv": [ 7.99, 15.01, 0.5, 15.5 ], "texture": "#0" },
				"up": { "uv": [ 0.5, 12, 8, 12.5 ], "texture": "#0", "rotation": 180 },
				"north": { "uv": [ 0.5, 12, 8, 15.5 ], "texture": "#0" },
				"west": { "uv": [ 7.51, 12.01, 7.99, 15.49 ], "texture": "#0" },
				"east": { "uv": [ 0.5, 12, 0.98, 15.48 ], "texture": "#0" }
			}
		},
		{
			"from": [ 14.00034, 4.499973, 10.99932 ],
			"to": [ 16.00034, 7.999973, 11.49932 ],
			"faces": {
				"down": { "uv": [ 14, 11, 15.99, 11.49 ], "texture": "#0" },
				"up": { "uv": [ 15.99, 8.01, 14, 8.5 ], "texture": "#0", "rotation": 180 },
				"south": { "uv": [ 14.01, 8, 16, 11.49 ], "texture": "#0" },
				"west": { "uv": [ 14, 8, 14.48, 11.48 ], "texture": "#0" },
				"east": { "uv": [ 15.51, 8.01, 15.99, 11.49 ], "texture": "#0" }
			}
		},
		{
			"from": [ 7.999964, 4.500941, 4.500683 ],
			"to": [ 12.99996, 8.000941, 5.000683 ],
			"faces": {
				"down": { "uv": [ 7.99, 11.01, 3, 11.5 ], "texture": "#0" },
				"up": { "uv": [ 7.99, 8.01, 3, 8.5 ], "texture": "#0" },
				"north": { "uv": [ 3, 8, 8, 11.5 ], "texture": "#0" },
				"west": { "uv": [ 7.51, 8.01, 7.99, 11.49 ], "texture": "#0" },
				"east": { "uv": [ 3, 8, 3.48, 11.48 ], "texture": "#0" }
			}
		},
		{
			"from": [ 13.49998, 4.500335, 4.500202 ],
			"to": [ 15.99998, 8.000335, 5.000202 ],
			"faces": {
				"down": { "uv": [ 2.5, 11, 0.009999752, 11.49 ], "texture": "#0" },
				"up": { "uv": [ 2.49, 8, 0, 8.49 ], "texture": "#0" },
				"north": { "uv": [ 0.01, 8.01, 2.5, 11.5 ], "texture": "#0" },
				"west": { "uv": [ 2, 8, 2.48, 11.48 ], "texture": "#0" },
				"east": { "uv": [ 0.01, 8.01, 0.49, 11.5 ], "texture": "#0" }
			}
		},
		{
			"from": [ 11.5006, 8.49942, 11.00009 ],
			"to": [ 16.0006, 11.99842, 11.50009 ],
			"faces": {
				"down": { "uv": [ 15.99, 7.01, 11.51, 7.49 ], "texture": "#0", "rotation": 180 },
				"up": { "uv": [ 15.99, 4.01, 11.51, 4.49 ], "texture": "#0", "rotation": 180 },
				"south": { "uv": [ 11.51, 4.01, 15.99, 7.49 ], "texture": "#0" },
				"west": { "uv": [ 11.51, 4.01, 11.99, 7.49 ], "texture": "#0" },
				"east": { "uv": [ 15.51, 4.01, 15.99, 7.49 ], "texture": "#0" }
			}
		},
		{
			"from": [ 7.999187, 8.500317, 11.00027 ],
			"to": [ 10.99919, 12.00032, 11.50027 ],
			"faces": {
				"down": { "uv": [ 8.01, 7.01, 10.99, 7.49 ], "texture": "#0" },
				"up": { "uv": [ 10.99, 4.01, 8.01, 4.49 ], "texture": "#0", "rotation": 180 },
				"south": { "uv": [ 8.01, 4.01, 10.99, 7.49 ], "texture": "#0" },
				"west": { "uv": [ 8.01, 4.01, 8.49, 7.49 ], "texture": "#0" },
				"east": { "uv": [ 10.51, 4.01, 10.99, 7.49 ], "texture": "#0" }
			}
		},
		{
			"from": [ 12.50098, 8.500035, 4.500215 ],
			"to": [ 16.00098, 12.00004, 5.000215 ],
			"faces": {
				"down": { "uv": [ 3.5, 7, 0, 7.5 ], "texture": "#0" },
				"up": { "uv": [ 3.5, 4, 0, 4.5 ], "texture": "#0" },
				"north": { "uv": [ 0.01029992, 4.01, 3.5, 7.5 ], "texture": "#0" },
				"west": { "uv": [ 3, 4, 3.48, 7.48 ], "texture": "#0" },
				"east": { "uv": [ 0.01, 4.01, 0.49, 7.49 ], "texture": "#0" }
			}
		},
		{
			"from": [ 8.000096, 12.50068, 10.999 ],
			"to": [ 15.5001, 16.00068, 11.499 ],
			"faces": {
				"down": { "uv": [ 8.01, 3.01, 15.5, 3.5 ], "texture": "#0" },
				"up": { "uv": [ 15.5, 0, 8, 0.5 ], "texture": "#0", "rotation": 180 },
				"south": { "uv": [ 8, 0, 15.5, 3.5 ], "texture": "#0" },
				"west": { "uv": [ 8, 0, 8.5, 3.5 ], "texture": "#0" },
				"east": { "uv": [ 15, 0, 15.5, 3.5 ], "texture": "#0" }
			}
		},
		{
			"from": [ 7.999325, 12.50042, 4.500894 ],
			"to": [ 10.49932, 16.00042, 5.000894 ],
			"faces": {
				"down": { "uv": [ 5.51, 3.01, 7.99, 3.49 ], "texture": "#0" },
				"up": { "uv": [ 5.5, 0, 7.98, 0.4799995 ], "texture": "#0", "rotation": 180 },
				"north": { "uv": [ 5.5, 0, 8, 3.5 ], "texture": "#0" },
				"west": { "uv": [ 7.5, 0, 8, 3.5 ], "texture": "#0" },
				"east": { "uv": [ 5.5, 0, 6, 3.5 ], "texture": "#0" }
			}
		},
		{
			"from": [ 11.00038, 12.49976, 4.499393 ],
			"to": [ 16.00038, 15.99976, 4.999393 ],
			"faces": {
				"down": { "uv": [ 4.99, 3.01, 0, 3.5 ], "texture": "#0" },
				"up": { "uv": [ 5, 0, 0.01000023, 0.4899998 ], "texture": "#0" },
				"north": { "uv": [ 0, 0, 5, 3.5 ], "texture": "#0" },
				"west": { "uv": [ 4.5, 0, 5, 3.5 ], "texture": "#0" },
				"east": { "uv": [ 0, 0, 0.5, 3.5 ], "texture": "#0" }
			}
		},
		{
			"from": [ 10.99968, -0.5004655, 5.500916 ],
			"to": [ 15.99968, -0.000465512, 11.00092 ],
			"faces": {
				"down": { "uv": [ 11, 5, 16, 10.5 ], "texture": "#2", "cullface": "down" },
				"north": { "uv": [ 11, 10, 16, 10.5 ], "texture": "#2", "cullface": "down", "rotation": 180 },
				"south": { "uv": [ 11, 5, 16, 5.5 ], "texture": "#2", "cullface": "down" },
				"west": { "uv": [ 11, 10.5, 11.5, 5 ], "texture": "#2", "cullface": "down", "rotation": 270 },
				"east": { "uv": [ 15.5, 10.5, 16, 5 ], "texture": "#2", "cullface": "down", "rotation": 90 }
			}
		},
		{
			"from": [ 8.00054, -0.5001861, 5.49962 ],
			"to": [ 10.50054, -0.000186086, 10.49962 ],
			"faces": {
				"down": { "uv": [ 8, 5.5, 10.5, 10.5 ], "texture": "#2", "cullface": "down" },
				"north": { "uv": [ 10.5, 10, 8, 10.5 ], "texture": "#2", "cullface": "down" },
				"south": { "uv": [ 8, 5.5, 10.5, 6 ], "texture": "#2", "cullface": "down" },
				"west": { "uv": [ 8, 5.5, 8.5, 10.5 ], "texture": "#2", "cullface": "down", "rotation": 90 },
				"east": { "uv": [ 10, 5.5, 10.5, 10.5 ], "texture": "#2", "cullface": "down", "rotation": 270 }
			}
		},
		{
			"from": [ 8.000706, 8.50059, 4.499887 ],
			"to": [ 12.00071, 12.00059, 4.999887 ],
			"faces": {
				"down": { "uv": [ 7.99, 7.01, 4, 7.5 ], "texture": "#0" },
				"up": { "uv": [ 7.99, 4.01, 4, 4.5 ], "texture": "#0" },
				"north": { "uv": [ 4, 4, 8, 7.5 ], "texture": "#0" },
				"west": { "uv": [ 7.51, 4.01, 7.99, 7.49 ], "texture": "#0" },
				"east": { "uv": [ 4, 4, 4.48, 7.48 ], "texture": "#0" }
			}
		},
		{
			"from": [ 7.99954, 4.499831, 11.00088 ],
			"to": [ 13.49954, 7.999831, 11.50088 ],
			"faces": {
				"down": { "uv": [ 8, 11, 13.5, 11.5 ], "texture": "#0" },
				"up": { "uv": [ 13.5, 8, 8, 8.5 ], "texture": "#0", "rotation": 180 },
				"south": { "uv": [ 8, 8, 13.5, 11.5 ], "texture": "#0" },
				"west": { "uv": [ 14, 8, 14.48, 11.48 ], "texture": "#0" },
				"east": { "uv": [ 13, 8, 13.48, 11.48 ], "texture": "#0" }
			}
		}
	]
}